LICENSE
MANIFEST.in
README.md
setup.cfg
setup.py
agape/__init__.py
agape/db.py
agape/entity.py
agape/errors.py
agape/models.py
agape/proxies.py
agape/routers.py
agape/serializers.py
agape/signals.py
agape/test.py
agape/views.py
agape/viewsets.py
agape/django/__init__.py
agape/django/config.py
agape_core.egg-info/PKG-INFO
agape_core.egg-info/SOURCES.txt
agape_core.egg-info/dependency_links.txt
agape_core.egg-info/requires.txt
agape_core.egg-info/top_level.txt